README.rst
setup.py
django_responsediff.egg-info/PKG-INFO
django_responsediff.egg-info/SOURCES.txt
django_responsediff.egg-info/dependency_links.txt
django_responsediff.egg-info/requires.txt
django_responsediff.egg-info/top_level.txt
responsediff/__init__.py
responsediff/exceptions.py
responsediff/response.py
responsediff/test.py
responsediff/tests/__init__.py
responsediff/tests/test_mixin.py
responsediff/tests/test_response.py
responsediff/tests/test_responsediff.py
responsediff/tests/project/__init__.py
responsediff/tests/project/settings.py
responsediff/tests/project/urls.py