Metadata-Version: 2.1
Name: django-responsediff
Version: 0.8.1
Summary: HTTP response diffing against fixtures for testing
Home-page: https://github.com/yourlabs/django-responsediff
Author: James Pic
Author-email: jamespic@gmail.com
License: MIT
Keywords: django test response fixture diff
Platform: UNKNOWN
Classifier: Development Status :: 4 - Beta
Classifier: Environment :: Web Environment
Classifier: Framework :: Django
Classifier: Intended Audience :: Developers
Classifier: License :: OSI Approved :: MIT License
Classifier: Operating System :: OS Independent
Classifier: Programming Language :: Python
Classifier: Programming Language :: Python :: 2
Classifier: Programming Language :: Python :: 3
Classifier: Topic :: Internet :: WWW/HTTP
Classifier: Topic :: Software Development :: Libraries :: Python Modules
